gradle.properties
hexdoc_hexmapping/__gradle_version__.py
hexdoc_hexmapping/__init__.py
hexdoc_hexmapping/__version__.py
hexdoc_hexmapping/_hooks.py
hexdoc_hexmapping/py.typed
hexdoc_hexmapping/_export/.gitignore
hexdoc_hexmapping/_export/__init__.py
hexdoc_hexmapping/_export/generated/__init__.py
hexdoc_hexmapping/_export/generated/hexmapping.hexdoc.json
hexdoc_hexmapping/_export/generated/hexmapping.patterns.hexdoc.json
hexdoc_hexmapping/_export/generated/assets/hexcasting/lang/en_us.flatten.json5
hexdoc_hexmapping/_export/generated/assets/hexcasting/patchouli_books/thehexbook/en_us/entries/casting/markers.json
hexdoc_hexmapping/_export/generated/assets/hexcasting/patchouli_books/thehexbook/en_us/entries/patterns/marker_actions.json
hexdoc_hexmapping/_export/generated/assets/hexcasting/patchouli_books/thehexbook/en_us/entries/patterns/spells/marker_spells.json
hexdoc_hexmapping/_export/generated/assets/hexmapping/lang/en_us.json
hexdoc_hexmapping/_export/generated/assets/hexmapping/lang/zh_cn.json
hexdoc_hexmapping/_export/generated/assets/hexmapping/textures/inline/markers/circle.png
hexdoc_hexmapping/_export/generated/assets/hexmapping/textures/inline/markers/icon.png
hexdoc_hexmapping/_export/generated/assets/hexmapping/textures/inline/markers/polygon.png
hexdoc_hexmapping/_export/generated/assets/hexmapping/textures/inline/markers/polyline.png
hexdoc_hexmapping/_export/generated/assets/hexmapping/textures/inline/markers/rectangle.png
hexdoc_hexmapping/_export/generated/data/hexcasting/tags/action/per_world_pattern.json
hexdoc_hexmapping/_templates/__init__.py
hexdoc_hexmapping/_templates/pages/patchouli/page.html.jinja
hexdoc_hexmapping-0.0.3.1.0.dev0.dist-info/METADATA
hexdoc_hexmapping-0.0.3.1.0.dev0.dist-info/WHEEL
hexdoc_hexmapping-0.0.3.1.0.dev0.dist-info/entry_points.txt
hexdoc_hexmapping-0.0.3.1.0.dev0.dist-info/licenses/LICENSE
hexdoc_hexmapping-0.0.3.1.0.dev0.dist-info/RECORD
