Metadata-Version: 2.4
Name: hexdoc-hexmapping
Version: 0.0.3.1.0.dev0
Summary: Python web book docgen and hexdoc plugin for HexMapping.
Project-URL: Homepage, https://techtastic.github.io/hexmapping
Project-URL: Source, https://github.com/TechTastic/hexmapping
Author: TechTastic
License-File: LICENSE
Keywords: hexdoc
Requires-Python: >=3.11
Requires-Dist: hexdoc-hexcasting~=0.11.2.1.0.dev20
Provides-Extra: dev
Requires-Dist: ruff~=0.1.4; extra == 'dev'
